test/__init__.py
test_pypi_action-3.2.dist-info/METADATA
test_pypi_action-3.2.dist-info/WHEEL
test_pypi_action-3.2.dist-info/top_level.txt
test_pypi_action-3.2.dist-info/RECORD
