Metadata-Version: 2.1
Name: test-pypi-action
Version: 3.2
Summary: To be deleted.
Home-page: https://github.com/PabloLec/test-pypi-action
Author: Pablo Lecolinet
Author-email: pablolec@pm.me
License: GNU GPLv3
Platform: UNKNOWN
